OBP_reliability_pillar_u1/__init__.py
OBP_reliability_pillar_u1/auto_scaling/__init__.py
OBP_reliability_pillar_u1/auto_scaling/asg_elb_healthcheck_required.py
OBP_reliability_pillar_u1/auto_scaling/compliance.py
OBP_reliability_pillar_u1/auto_scaling/launch_config_public_ip_disabled.py
OBP_reliability_pillar_u1/cloudwatch/__init__.py
OBP_reliability_pillar_u1/cloudwatch/alarm_action_check.py
OBP_reliability_pillar_u1/cloudwatch/compliance.py
OBP_reliability_pillar_u1/dynamodb/__init__.py
OBP_reliability_pillar_u1/dynamodb/compliance.py
OBP_reliability_pillar_u1/dynamodb/dynamodb_autoscaling_enabled.py
OBP_reliability_pillar_u1/dynamodb/dynamodb_pitr_enabled.py
OBP_reliability_pillar_u1/dynamodb/utils.py
OBP_reliability_pillar_u1/ec2/__init__.py
OBP_reliability_pillar_u1/ec2/compliance.py
OBP_reliability_pillar_u1/ec2/ec2_instance_detailed_monitoring_enabled.py
OBP_reliability_pillar_u1/ec2/instance_in_vpc.py
OBP_reliability_pillar_u1/elastic_beanstalk/__init__.py
OBP_reliability_pillar_u1/elastic_beanstalk/compliance.py
OBP_reliability_pillar_u1/elastic_beanstalk/enhanced_health_reporting_enabled.py
OBP_reliability_pillar_u1/elastic_load_balancer/__init__.py
OBP_reliability_pillar_u1/elastic_load_balancer/compliance.py
OBP_reliability_pillar_u1/elastic_load_balancer/cross_zone_load_balancing_enabled.py
OBP_reliability_pillar_u1/elastic_load_balancer/elb_deletion_protection.py
OBP_reliability_pillar_u1/elastic_load_balancer/utils.py
OBP_reliability_pillar_u1/elastic_search/__init__.py
OBP_reliability_pillar_u1/elastic_search/compliance.py
OBP_reliability_pillar_u1/elastic_search/elastic_search_in_vpc_only.py
OBP_reliability_pillar_u1/guard_duty/__init__.py
OBP_reliability_pillar_u1/guard_duty/compliance.py
OBP_reliability_pillar_u1/guard_duty/guard_duty_enabled.py
OBP_reliability_pillar_u1/lambdafn/__init__.py
OBP_reliability_pillar_u1/lambdafn/compliance.py
OBP_reliability_pillar_u1/lambdafn/lambda_dlq_check.py
OBP_reliability_pillar_u1-0.2.2.dist-info/LICENCE
OBP_reliability_pillar_u1-0.2.2.dist-info/METADATA
OBP_reliability_pillar_u1-0.2.2.dist-info/WHEEL
OBP_reliability_pillar_u1-0.2.2.dist-info/top_level.txt
OBP_reliability_pillar_u1-0.2.2.dist-info/RECORD
