Metadata-Version: 2.1
Name: OBP_reliability_pillar_u1
Version: 0.2.2
Summary: Provides AWS compliance details
Author-email: "dheeraj.banodha" <dheerajmbanodha@gmail.com>
Classifier: Programming Language :: Python :: 3
Classifier: Operating System :: OS Independent
Requires-Python: >=3.7
License-File: LICENCE
Requires-Dist: boto3
Requires-Dist: pytz
